{
  "type": "brewinandchewin:fermenting",
  "ingredients": [
    {
      "item": "minecraft:honey_bottle"
    },
    {
      "item": "minecraft:glow_ink_sac"
    },
    {
      "item": "minecraft:glowstone_dust"
    },
    {
      "item": "minecraft:glow_berries"
    }
  ],
  "result": {
    "item": "bundledelight:glittering_grenadine_glass"
  },
  "container": {
    "item": "bundledelight:glass_tankard"
  },
  "liquid": {
    "item": "minecraft:water_bucket"
  },
  "experience": 0.6,
  "cookingtime": 12000,
  "temperature": 2
}